ndx_probeinterface/__init__.py
ndx_probeinterface/io.py
ndx_probeinterface/version.py
ndx_probeinterface/spec/ndx-probeinterface.extensions.yaml
ndx_probeinterface/spec/ndx-probeinterface.namespace.yaml
ndx_probeinterface-0.2.0.dist-info/licenses/LICENSE.txt
ndx_probeinterface-0.2.0.dist-info/METADATA
ndx_probeinterface-0.2.0.dist-info/WHEEL
ndx_probeinterface-0.2.0.dist-info/top_level.txt
ndx_probeinterface-0.2.0.dist-info/RECORD
