Metadata-Version: 2.4
Name: ndx-probeinterface
Version: 0.2.0
Summary: Extension for defining neural probes in the probeinterface format
Home-page: 
Author: Alessio Buccino, Kyu Hyun Lee, Geeling Chau
Author-email: alessiop.buccino@gmail.com
License: MIT
Keywords: NeurodataWithoutBorders,NWB,nwb-extension,ndx-extension
Classifier: Intended Audience :: Developers
Classifier: Intended Audience :: Science/Research
Classifier: License :: OSI Approved :: MIT License
License-File: LICENSE.txt
Requires-Dist: hdmf>=3.1.1
Requires-Dist: pynwb>=2.0.0
Requires-Dist: probeinterface>=0.2.18
Dynamic: author
Dynamic: author-email
Dynamic: classifier
Dynamic: description
Dynamic: description-content-type
Dynamic: keywords
Dynamic: license
Dynamic: license-file
Dynamic: requires-dist
Dynamic: summary
